flowtutor/__init__.py
flowtutor/codegenerator.py
flowtutor/containers.py
flowtutor/language_service.py
flowtutor/main.py
flowtutor/modal_service.py
flowtutor/py.typed
flowtutor/settings_service.py
flowtutor/util_service.py
flowtutor/debugger/__init__.py
flowtutor/debugger/debugsession.py
flowtutor/debugger/ftdb.py
flowtutor/debugger/ftdbsession.py
flowtutor/debugger/gdbsession.py
flowtutor/debugger/stdinqueue.py
flowtutor/flowchart/__init__.py
flowtutor/flowchart/connection.py
flowtutor/flowchart/connector.py
flowtutor/flowchart/flowchart.py
flowtutor/flowchart/functionend.py
flowtutor/flowchart/functionstart.py
flowtutor/flowchart/node.py
flowtutor/flowchart/parameter.py
flowtutor/flowchart/struct_definition.py
flowtutor/flowchart/struct_member.py
flowtutor/flowchart/template.py
flowtutor/flowchart/type_definition.py
flowtutor/gui/__init__.py
flowtutor/gui/debugger.py
flowtutor/gui/gui.py
flowtutor/gui/menubar_main.py
flowtutor/gui/section_node_extras.py
flowtutor/gui/section_structs.py
flowtutor/gui/section_typedefs.py
flowtutor/gui/sidebar.py
flowtutor/gui/sidebar_functionend.py
flowtutor/gui/sidebar_functionstart.py
flowtutor/gui/sidebar_multi.py
flowtutor/gui/sidebar_none.py
flowtutor/gui/sidebar_template.py
flowtutor/gui/window_types.py
flowtutor/gui/assets/__init__.py
flowtutor/gui/assets/c.png
flowtutor/gui/assets/hammer.png
flowtutor/gui/assets/inconsolata.ttf
flowtutor/gui/assets/pencil.png
flowtutor/gui/assets/python.png
flowtutor/gui/assets/run.png
flowtutor/gui/assets/step_into.png
flowtutor/gui/assets/step_over.png
flowtutor/gui/assets/stop.png
flowtutor/gui/assets/trash.png
flowtutor/templates/__init__.py
flowtutor/templates/c/assignment.template.json
flowtutor/templates/c/call.template.json
flowtutor/templates/c/close_file.template.json
flowtutor/templates/c/conditional.jinja
flowtutor/templates/c/conditional.template.json
flowtutor/templates/c/declaration.template.json
flowtutor/templates/c/dowhileloop.jinja
FlowTutor-0.11.1.dist-info/LICENSE
FlowTutor-0.11.1.dist-info/METADATA
FlowTutor-0.11.1.dist-info/WHEEL
FlowTutor-0.11.1.dist-info/entry_points.txt
FlowTutor-0.11.1.dist-info/top_level.txt
FlowTutor-0.11.1.dist-info/RECORD
