Metadata-Version: 2.1
Name: FlowTutor
Version: 0.11.1
Summary: A graphical programming environment using flowcharts.
Author-email: Thomas Rößl <e11775192@student.tuwien.ac.at>
Project-URL: Documentation, https://github.com/thomasroessl/FlowTutor/wiki
Project-URL: Source, https://github.com/thomasroessl/FlowTutor
Project-URL: Changelog, https://github.com/thomasroessl/FlowTutor/releases
Classifier: Development Status :: 3 - Alpha
Classifier: Programming Language :: Python :: 3
Classifier: Programming Language :: Python :: 3 :: Only
Classifier: Programming Language :: Python :: 3.9
Classifier: Programming Language :: Python :: 3.10
Classifier: Programming Language :: Python :: 3.11
Classifier: Programming Language :: Python :: 3.12
Classifier: Operating System :: OS Independent
Classifier: Topic :: Education
Classifier: Topic :: Software Development
Classifier: Intended Audience :: Education
Classifier: License :: OSI Approved :: GNU Lesser General Public License v3 (LGPLv3)
Requires-Python: <3.13,>=3.9
License-File: LICENSE
Requires-Dist: platformdirs >=4.2
Requires-Dist: blinker >=1.8
Requires-Dist: dearpygui >=1.11
Requires-Dist: Shapely >=2.0
Requires-Dist: dependency-injector-fork >=4.42
Requires-Dist: pygdbmi >=0.11
Requires-Dist: urllib3 >=2.2
Requires-Dist: Jinja2 >=3.1
Provides-Extra: deployment
Requires-Dist: pynsist >=2.8 ; extra == 'deployment'
Requires-Dist: twine >=5.0 ; extra == 'deployment'
Requires-Dist: build >=1.2 ; extra == 'deployment'
Provides-Extra: testing
Requires-Dist: pytest >=8.2 ; extra == 'testing'
Requires-Dist: pytest-cov >=5.0 ; extra == 'testing'
Requires-Dist: mypy >=1.10 ; extra == 'testing'
Requires-Dist: flake8 >=7.0 ; extra == 'testing'
Requires-Dist: tox >=4.15 ; extra == 'testing'
